polcart/__init__.py
polcart/polcart.py
polcart/test_polcart.py
polcart-2017.8.26.10.50.dist-info/DESCRIPTION.rst
polcart-2017.8.26.10.50.dist-info/METADATA
polcart-2017.8.26.10.50.dist-info/RECORD
polcart-2017.8.26.10.50.dist-info/WHEEL
polcart-2017.8.26.10.50.dist-info/metadata.json
polcart-2017.8.26.10.50.dist-info/top_level.txt
